apteco_api/__init__.py
apteco_api/api_client.py
apteco_api/configuration.py
apteco_api/exceptions.py
apteco_api/rest.py
apteco_api/api/__init__.py
apteco_api/api/about_api.py
apteco_api/api/audience_compositions_api.py
apteco_api/api/audience_hits_api.py
apteco_api/api/audience_settings_api.py
apteco_api/api/audiences_api.py
apteco_api/api/collection_hits_api.py
apteco_api/api/collections_api.py
apteco_api/api/cubes_api.py
apteco_api/api/dashboards_api.py
apteco_api/api/data_licensing_api.py
apteco_api/api/directories_api.py
apteco_api/api/exports_api.py
apteco_api/api/external_login_api.py
apteco_api/api/fast_stats_builds_api.py
apteco_api/api/fast_stats_jobs_api.py
apteco_api/api/fast_stats_systems_api.py
apteco_api/api/files_api.py
apteco_api/api/groups_api.py
apteco_api/api/people_stage_api.py
apteco_api/api/permissions_api.py
apteco_api/api/queries_api.py
apteco_api/api/sessions_api.py
apteco_api/api/settings_api.py
apteco_api/api/shares_api.py
apteco_api/api/static_resources_api.py
apteco_api/api/teams_api.py
apteco_api/api/telemetry_api.py
apteco_api/api/temporary_files_api.py
apteco_api/api/themes_api.py
apteco_api/api/user_registration_requests_api.py
apteco_api/api/user_reset_password_requests_api.py
apteco_api/api/users_api.py
apteco_api/api/visualisations_api.py
apteco_api/models/__init__.py
apteco_api/models/abstract_render_spec.py
apteco_api/models/age_rule.py
apteco_api/models/audience_calculate_job_detail.py
apteco_api/models/audience_check_detail.py
apteco_api/models/audience_check_job_detail.py
apteco_api/models/audience_data_licensing_info_job_detail.py
apteco_api/models/audience_detail.py
apteco_api/models/audience_export_detail.py
apteco_api/models/audience_export_job_detail.py
apteco_api/models/audience_hit_detail.py
apteco_api/models/audience_hit_summary.py
apteco_api/models/audience_query_result.py
apteco_api/models/audience_result_detail.py
apteco_api/models/audience_result_summary.py
apteco_api/models/audience_settings_detail.py
apteco_api-0.3.2.dist-info/LICENSE
apteco_api-0.3.2.dist-info/METADATA
apteco_api-0.3.2.dist-info/WHEEL
apteco_api-0.3.2.dist-info/top_level.txt
apteco_api-0.3.2.dist-info/RECORD
