Metadata-Version: 2.1
Name: apteco-api
Version: 0.3.2
Summary: Apteco API
Home-page: https://www.apteco.com/
Author: Apteco Ltd
Author-email: support@apteco.com
License: Apache 2.0
Keywords: Apteco,Apteco API,Apteco Marketing Suite,Apteco FastStats,FastStats,Apteco Orbit,Orbit,OpenAPI,OpenAPI-Generator,Swagger,Swagger API,API,REST
Platform: UNKNOWN
Classifier: License :: OSI Approved :: Apache Software License
Classifier: Development Status :: 4 - Beta
Classifier: Programming Language :: Python :: 3
Classifier: Programming Language :: Python :: 3.4
Classifier: Programming Language :: Python :: 3.5
Classifier: Programming Language :: Python :: 3.6
Classifier: Programming Language :: Python :: 3.7
Requires-Dist: urllib3 (>=1.15)
Requires-Dist: six (>=1.10)
Requires-Dist: certifi
Requires-Dist: python-dateutil
